{
  "source": "cut3",
  "stats": {
    "width": 640,
    "height": 480,
    "totalPixels": 307200,
    "paletteSize": 256,
    "uniqueColorsUsed": 248,
    "mostUsedColor": 255,
    "hasRAW": true,
    "rawSize": 921600
  },
  "palette": [
    "#ffffff",
    "#080808",
    "#101010",
    "#181818",
    "#d6d6d6",
    "#efe7e7",
    "#ffe7e7",
    "#ffd6d6",
    "#ffbdbd",
    "#6b4a4a",
    "#ffadad",
    "#181010",
    "#ff9494",
    "#ff8c8c",
    "#100808",
    "#ff7b7b",
    "#ff6363",
    "#180808",
    "#311010",
    "#ff5252",
    "#6b2121",
    "#842121",
    "#421010",
    "#ad2929",
    "#ff3939",
    "#9c2121",
    "#290808",
    "#5a1010",
    "#bd2121",
    "#ef2929",
    "#ff2929",
    "#de2121",
    "#b51818",
    "#ff2121",
    "#420808",
    "#841010",
    "#9c1010",
    "#ef1818",
    "#5a0808",
    "#630808",
    "#c61010",
    "#6b0808",
    "#d61010",
    "#7b0808",
    "#ff1010",
    "#8c0808",
    "#940808",
    "#b50808",
    "#080000",
    "#de2118",
    "#7b1008",
    "#731810",
    "#731008",
    "#5a1008",
    "#e7bdb5",
    "#391008",
    "#ad3921",
    "#bd2908",
    "#391810",
    "#c64a29",
    "#943118",
    "#ce4221",
    "#842108",
    "#b52908",
    "#c68c7b",
    "#c65231",
    "#843118",
    "#b54221",
    "#bd4221",
    "#ad3918",
    "#9c2908",
    "#e7b5a5",
    "#8c5a4a",
    "#422921",
    "#6b3929",
    "#ce6b4a",
    "#c64218",
    "#6b2108",
    "#e7a58c",
    "#c6846b",
    "#ad6b52",
    "#a5634a",
    "#de8463",
    "#5a3121",
    "#8c4a31",
    "#de734a",
    "#844229",
    "#7b3921",
    "#9c4221",
    "#421808",
    "#e7ad94",
    "#c68c73",
    "#ad735a",
    "#a56b52",
    "#de8c6b",
    "#6b4231",
    "#ce7b5a",
    "#8c5239",
    "#bd6b4a",
    "#d6734a",
    "#ad5a39",
    "#ce6b42",
    "#733921",
    "#c66339",
    "#6b3118",
    "#4a2110",
    "#632910",
    "#de9473",
    "#ce8463",
    "#8c5a42",
    "#5a3929",
    "#c67b5a",
    "#bd7352",
    "#b56b4a",
    "#291810",
    "#ce734a",
    "#c66b42",
    "#9c5231",
    "#6b3921",
    "#944a29",
    "#b55a31",
    "#211008",
    "#843918",
    "#391808",
    "#5a2108",
    "#311000",
    "#decec6",
    "#e7b59c",
    "#d6a58c",
    "#bd8c73",
    "#de9c7b",
    "#d69473",
    "#9c6b52",
    "#ce8c6b",
    "#94634a",
    "#c68463",
    "#634231",
    "#bd7b5a",
    "#b57352",
    "#de8c63",
    "#845239",
    "#ad6b4a",
    "#c6734a",
    "#9c5a39",
    "#734229",
    "#bd6b42",
    "#945231",
    "#4a2918",
    "#b56339",
    "#633118",
    "#5a2910",
    "#dea584",
    "#d69c7b",
    "#bd8463",
    "#845a42",
    "#b57b5a",
    "#d68c63",
    "#a56b4a",
    "#9c6342",
    "#c67b52",
    "#945a39",
    "#633921",
    "#ad6339",
    "#a55a31",
    "#bd6331",
    "#733918",
    "#d6bdad",
    "#e7b594",
    "#c69473",
    "#7b5239",
    "#c6845a",
    "#4a3121",
    "#bd7b52",
    "#ad6b42",
    "#845231",
    "#945229",
    "#4a2108",
    "#d69c73",
    "#c68c63",
    "#b57b52",
    "#946342",
    "#ad734a",
    "#94735a",
    "#8c6b52",
    "#84634a",
    "#c6bdb5",
    "#847b73",
    "#6b5a4a",
    "#4a2908",
    "#cea573",
    "#6b5231",
    "#4a3921",
    "#7b5218",
    "#e7d6bd",
    "#9c7b4a",
    "#846331",
    "#ad946b",
    "#bda573",
    "#debd7b",
    "#9c7b39",
    "#6b5221",
    "#c6a55a",
    "#8c7339",
    "#a58439",
    "#846318",
    "#e7d6ad",
    "#b5a57b",
    "#94845a",
    "#e7ce8c",
    "#a58c4a",
    "#c6a552",
    "#947b39",
    "#8c7b4a",
    "#ceb56b",
    "#ad944a",
    "#cebd84",
    "#7b6b39",
    "#736331",
    "#d6c68c",
    "#c6b573",
    "#bda552",
    "#efe7c6",
    "#d6cead",
    "#736b4a",
    "#ad9c52",
    "#c6b563",
    "#b5a55a",
    "#5a5229",
    "#8c8452",
    "#e7e7de",
    "#949473",
    "#8c8c63",
    "#636331",
    "#c6cece",
    "#525a5a",
    "#4a5252",
    "#424a4a",
    "#394242",
    "#313939",
    "#293131",
    "#182121",
    "#103139",
    "#4a636b",
    "#001821",
    "#7b8c94",
    "#294a5a",
    "#520810",
    "#ffff99",
    "#ffff66",
    "#ffff33",
    "#ffff00",
    "#ffcc00",
    "#cc9900",
    "#663399",
    "#111111",
    "#000000"
  ]
}