{
  "source": "cut4",
  "stats": {
    "width": 640,
    "height": 480,
    "totalPixels": 307200,
    "paletteSize": 256,
    "uniqueColorsUsed": 249,
    "mostUsedColor": 255,
    "hasRAW": true,
    "rawSize": 921600
  },
  "palette": [
    "#ffffff",
    "#292929",
    "#313131",
    "#393939",
    "#424242",
    "#4a4a4a",
    "#525252",
    "#5a5a5a",
    "#636363",
    "#6b6b6b",
    "#7b7b7b",
    "#8c8c8c",
    "#9c9c9c",
    "#a5a5a5",
    "#adadad",
    "#b5b5b5",
    "#cecece",
    "#d6d6d6",
    "#dedede",
    "#e7e7e7",
    "#efefef",
    "#f7f7f7",
    "#f7efef",
    "#e7dede",
    "#c6bdbd",
    "#292121",
    "#423131",
    "#211818",
    "#181010",
    "#100808",
    "#9c7363",
    "#7b5242",
    "#392118",
    "#ce947b",
    "#c68c73",
    "#b57b63",
    "#ad735a",
    "#734a39",
    "#945a42",
    "#debdad",
    "#d6b5a5",
    "#6b5a52",
    "#63524a",
    "#4a3931",
    "#ce9c84",
    "#c67b5a",
    "#7b6b63",
    "#e7c6b5",
    "#5a4a42",
    "#c6947b",
    "#6b4a39",
    "#c68463",
    "#e7946b",
    "#845239",
    "#ad6b4a",
    "#d6845a",
    "#a56342",
    "#9c5a39",
    "#734229",
    "#d6c6bd",
    "#e7bda5",
    "#524239",
    "#c69c84",
    "#efb594",
    "#bd8463",
    "#845a42",
    "#312118",
    "#d68c63",
    "#ce845a",
    "#9c6342",
    "#ad9484",
    "#cea58c",
    "#e7a57b",
    "#de9c73",
    "#523929",
    "#4a3121",
    "#bd7b52",
    "#845231",
    "#c6ad9c",
    "#9c8473",
    "#846b5a",
    "#dead8c",
    "#bd8c6b",
    "#9c6b4a",
    "#422918",
    "#392110",
    "#efceb5",
    "#e7bd9c",
    "#634229",
    "#deb594",
    "#cebdad",
    "#c6b5a5",
    "#a59484",
    "#8c7b6b",
    "#847363",
    "#9c948c",
    "#decebd",
    "#bdad9c",
    "#5a524a",
    "#524a42",
    "#9c8c7b",
    "#948473",
    "#ceb59c",
    "#7b6b5a",
    "#393129",
    "#736352",
    "#9c846b",
    "#312921",
    "#312110",
    "#292118",
    "#ad9c84",
    "#c6b59c",
    "#84735a",
    "#b5a58c",
    "#94846b",
    "#c6bdad",
    "#635a4a",
    "#ded6c6",
    "#cec6b5",
    "#b5ad9c",
    "#948c7b",
    "#524a39",
    "#cecec6",
    "#6b6b63",
    "#5a5a52",
    "#393931",
    "#efefc6",
    "#b5bdbd",
    "#949c9c",
    "#424a4a",
    "#000808",
    "#00cede",
    "#bdeff7",
    "#29525a",
    "#009cbd",
    "#4aa5bd",
    "#007ba5",
    "#006b94",
    "#b5deef",
    "#00638c",
    "#adc6d6",
    "#8ca5b5",
    "#8cadc6",
    "#00315a",
    "#b5c6d6",
    "#7b8c9c",
    "#738494",
    "#adb5bd",
    "#6b737b",
    "#636b73",
    "#8c9cad",
    "#8494a5",
    "#6b7b8c",
    "#849cb5",
    "#7b94ad",
    "#738ca5",
    "#212931",
    "#103152",
    "#000810",
    "#525a63",
    "#184273",
    "#9cbde7",
    "#94b5de",
    "#84adde",
    "#739cce",
    "#395a84",
    "#295284",
    "#21528c",
    "#2963ad",
    "#b5c6de",
    "#b5ceef",
    "#a5bdde",
    "#9cb5d6",
    "#637b9c",
    "#7ba5de",
    "#6b94ce",
    "#638cc6",
    "#5a84bd",
    "#314a6b",
    "#5a8cce",
    "#183152",
    "#29528c",
    "#102139",
    "#214a84",
    "#215294",
    "#10294a",
    "#bdcee7",
    "#94b5e7",
    "#84a5d6",
    "#394a63",
    "#6384b5",
    "#4a6b9c",
    "#5284ce",
    "#315284",
    "#4273bd",
    "#427bce",
    "#214273",
    "#3973c6",
    "#3163ad",
    "#295aa5",
    "#18396b",
    "#cedef7",
    "#c6d6ef",
    "#adc6ef",
    "#94add6",
    "#4a5a73",
    "#526b94",
    "#6b94d6",
    "#39527b",
    "#5a84c6",
    "#527bbd",
    "#5284d6",
    "#426bad",
    "#396bbd",
    "#3163b5",
    "#18315a",
    "#081831",
    "#dee7f7",
    "#5a6373",
    "#7b9cd6",
    "#6384bd",
    "#5273ad",
    "#42639c",
    "#3963ad",
    "#315aa5",
    "#21427b",
    "#29529c",
    "#bdceef",
    "#7b94c6",
    "#5a73a5",
    "#314263",
    "#395a9c",
    "#315294",
    "#18294a",
    "#ced6e7",
    "#4a5263",
    "#101829",
    "#313952",
    "#081029",
    "#d6d6de",
    "#84848c",
    "#efefff",
    "#52525a",
    "#5a5a63",
    "#4a4a52",
    "#42424a",
    "#4a4a5a",
    "#ffff99",
    "#ffff66",
    "#ffff33",
    "#ffff00",
    "#ffcc00",
    "#cc9900",
    "#663399",
    "#111111",
    "#000000"
  ]
}